<?xml version="1.0" encoding="utf-8"?>
<LanguageData>
  <DankPyon_Forest_Faction.pawnSingular>Árbol</DankPyon_Forest_Faction.pawnSingular>
  <DankPyon_Forest_Faction.pawnsPlural>Árboles</DankPyon_Forest_Faction.pawnsPlural>
  <DankPyon_Forest_Faction.fixedName>Criaturas del Bosque</DankPyon_Forest_Faction.fixedName>
  <DankPyon_Forest_Faction.label>El Bosque</DankPyon_Forest_Faction.label>
  <DankPyon_Forest_Faction.description>Monstruos y criaturas inhumanas que viven en las profundidades del bosque. Conocidos por cazar humanos indiscriminadamente y, sin embargo, albergar pacíficamente a los animales de la naturaleza.</DankPyon_Forest_Faction.description>
  <DankPyon_Witch_Faction.pawnSingular>Árbol</DankPyon_Witch_Faction.pawnSingular>
  <DankPyon_Witch_Faction.pawnsPlural>Árboles</DankPyon_Witch_Faction.pawnsPlural>
  <DankPyon_Witch_Faction.fixedName>Brujas Encantadas</DankPyon_Witch_Faction.fixedName>
  <DankPyon_Witch_Faction.label>Brujas Encantadas</DankPyon_Witch_Faction.label>
  <DankPyon_Witch_Faction.description>Monstruos y criaturas inhumanas que viven en las profundidades del bosque. Conocidos por cazar humanos indiscriminadamente y, sin embargo, albergar pacíficamente a los animales de la naturaleza.</DankPyon_Witch_Faction.description>
</LanguageData>
